{
  "id": "ventoy-multi-boot-usb-drag-drop",
  "title": "Ventoy: Solusi Terbaik Membuat Multi-Boot USB, Cukup Drag & Drop ISO! | Layar Kosong",
  "slug": "ventoy-multi-boot-usb-drag-drop.html",
  "url": "https://dalam.web.id/artikel/ventoy-multi-boot-usb-drag-drop.html",
  "datePublished": "2025-12-10T17:06:27.414+00:00",
  "summary": "Mengenal Ventoy, tool open source yang memungkinkan kamu membuat USB multi-boot untuk ISO/WIM/VHD(x) tanpa perlu format berulang. Mendukung 1300+ OS.",
  "category": "🐧 Linux & Open Source",
  "promptHint": "Ventoy fungsi?; Ventoy multi-boot?; Ventoy ISO?",
  "imageUrl": "https://www.ventoy.net/static/img/screen/screen_uefi.png",
  "content_plain": "Ventoy **Ventoy** adalah *tool* sumber terbuka (open source) yang diciptakan untuk membuat *bootable* USB *drive* yang ajaib. Kenapa ajaib? Karena kamu bisa boot langsung dari file **ISO/WIM/IMG/VHD(x)/EFI**! **Fokus Utama:** Kamu tidak perlu repot-repot memformat disk berulang kali. Cukup **seret dan lepas** file gambar OS (ISO, dll.) ke USB *drive* kamu, dan *boot*! Kamu bisa menyalin banyak file sekaligus, dan Ventoy akan otomatis menyajikan menu *boot* yang cantik untuk memilih OS mana yang ingin kamu jalankan. Mendukung arsitektur **x86 Legacy BIOS, IA32 UEFI, x86_64 UEFI, ARM64 UEFI, dan MIPS64EL UEFI** secara mulus. Mendukung gaya partisi **MBR dan GPT** dengan cara yang sama. Sudah menguji **1300+ ISO** (Lihat Daftar) dan mendukung **90%+ distro** di DistroWatch.com. **Website Resmi:** https://www.ventoy.net OS yang Sudah Diuji dan Siap Tempur Bayangkan, sebagai seorang **Human Resources Generalized** di dunia teknologi, Ventoy adalah *tool* wajib untuk memastikan semua tim punya akses ke OS yang mereka butuhkan. Berikut adalah daftar raksasa OS yang sudah diuji (dan berhasil) di Ventoy: Windows & WinPE Mendukung penuh semua versi modern Windows: Windows 7 hingga Windows 11 Windows Server 2012 hingga 2025 WinPE (Windows Preinstallation Environment) Unix (BSD, Firewall, dll.) Termasuk keluarga FreeBSD dan *appliances* jaringan: DragonFly, FreeBSD, pfSense, OPNsense GhostBSD, TrueNAS, XigmaNAS, FuryBSD, HardenedBSD MidnightBSD, ClonOS, EmergencyBootKit, helloSystem ChromeOS & Lainnya FydeOS, CloudReady, ChromeOS Flex, ThoriumOS VMware ESXi, Citrix XenServer, Xen XCP-ng Dan masih banyak lagi... Dunia Linux (Distro Raksasa!) Daftarnya panjang, Bosku, ini hanya beberapa *highlight* (sekitar 1300+ ISO sudah diuji!): Debian, Ubuntu, RHEL (6-10), CentOS, Fedora, openSUSE, SLES Arch, Manjaro, ArchLabs, EndeavourOS, ArcoLinux NixOS (Wah, favorit kita!), Pop OS, Zorin, Mint, Kali, Tails Proxmox VE, OpenWrt, Clear Linux, Garuda Linux, SteamOS, dll. Fitur-Fitur Ventoy yang Bikin Hidup Lebih Mudah Ventoy tidak hanya cepat (hanya dibatasi oleh kecepatan *copy* file ISO kamu), tetapi juga penuh dengan fitur canggih yang dibutuhkan oleh seorang *sysadmin* atau pengoprek serius: **100% Open Source.** Transparan dan bisa diverifikasi. **Auto Installation:** Dukungan *script* instalasi otomatis untuk Windows dan Linux. **Boot Langsung:** Boot langsung dari ISO/WIM/IMG/VHD(x)/EFI tanpa perlu proses ekstraksi. **Dukungan File System Luas:** Mendukung **FAT32/exFAT/NTFS/UDF/XFS/Ext2(3)(4)** untuk partisi utama. **Instalasi Fleksibel:** Bisa dipasang di USB, Local Disk, SSD, NVMe, atau SD Card. **ISO Besar:** Mendukung file ISO yang ukurannya **lebih besar dari 4GB**. **Menu Canggih:** Ada *Menu alias*, *Password protect*, mode *TreeView*, dan *highly customizable theme*. **Nondestructive Upgrade:** Data di USB kamu aman saat upgrade versi Ventoy. **Persistence:** Dukungan Persistence untuk Linux (menyimpan perubahan sesi). **Secure Boot:** Didukung untuk IA32/x86_64 UEFI. **VentoyPlugson:** GUI configurator untuk mengelola *plugin*. Tampilan Menu Boot UEFI Ventoy **Ventoy Compatible Concept:** Ventoy punya konsep unik. Selama file kamu kompatibel dengan Ventoy, kamu **tidak perlu mengupdate Ventoy** di USB kamu hanya karena ada distro Linux baru yang dirilis. Cukup *copy* file ISO-nya, dan beres! Instalasi dan Dokumentasi Resmi Panduan Instalasi Untuk panduan instalasi mendetail (termasuk cara *build* dari *source*), silakan merujuk ke situs resmi. Prosesnya sangat mudah, terutama bagi pengguna Windows dan Linux yang sudah terbiasa dengan *tool* semacam ini. Slogan **Go Back To Door** kamu akan jadi *copy-paste* ke USB, bukan ke mesin virtual! 😉 **Instruksi Instalasi:** Lihat di sini **Instruksi Compile dari Source:** Lihat BuildVentoyFromSource.txt Dokumentasi Lengkap Ventoy Berikut adalah *link* dokumentasi resmi Ventoy yang akan membantu kamu memaksimalkan semua fitur canggihnya, dari *Secure Boot* hingga *Persistence* dan *Custom Theme*. Judul Dokumentasi Link (Situs Resmi Ventoy) **Install & Update**https://www.ventoy.net/en/doc_start.html **Secure Boot**https://www.ventoy.net/en/doc_secure.html **Customize Theme**https://www.ventoy.net/en/plugin_theme.html **Linux Persistence**https://www.ventoy.net/en/plugin_persistence.html **Windows VHD Boot**https://www.ventoy.net/en/plugin_vhdboot.html **VentoyPlugson (GUI Plugin Configurator)**https://www.ventoy.net/en/plugin_plugson.html **FAQ**https://www.ventoy.net/en/faq.html Dukung Pengembangan Ventoy (Donasi) Sebagai *tool* open source yang luar biasa, jika kamu merasa terbantu, sangat dianjurkan untuk memberikan donasi kepada pengembangnya. **Kopi Susu** yang enak membutuhkan biaya, dan kode yang hebat juga butuh *support*! Pilihan Donasi Alipay WeChat Pay PayPal: Transfer ke akun admin@ventoy.net atau klik https://www.paypal.me/ventoy Bitcoin: Address: 19mZDWzZgzkHCi9YX9H3fYCUuCHq3W6wfT Diskusi dan Pengalaman Menggunakan Ventoy Ventoy punya forum aktif yang bisa kamu kunjungi: https://forums.ventoy.net. Kalau di sini, mari kita bahas pengalaman kita pakai *multi-boot* di USB *drive* favorit kita!"
}